diptest/.diptest.py.un~
diptest/__init__.py
diptest/consts.py
diptest/diptest.py
diptest/lib/_diptest_core.cpython-310-x86_64-linux-gnu.so
diptest.libs/libgomp-870cb1d0.so.1.0.0
diptest-0.10.0.dist-info/METADATA
diptest-0.10.0.dist-info/WHEEL
diptest-0.10.0.dist-info/RECORD
diptest-0.10.0.dist-info/licenses/COPYING
diptest-0.10.0.dist-info/licenses/LICENSE
