Metadata-Version: 2.2
Name: diptest
Version: 0.10.0
Summary: Hartigan's diptest.
Author-Email: Ralph Urlus <rurlus.dev@email.com>
License: GPLv2+
Project-URL: Source, https://github.com/RUrlus/diptest
Project-URL: Documentation, https://github.com/RUrlus/diptest#readme
Project-URL: Issues, https://github.com/RUrlus/diptest/issues
Requires-Python: >=3.8
Requires-Dist: psutil
Requires-Dist: numpy>=1.18
Provides-Extra: test
Requires-Dist: pytest; extra == "test"
